Mobydoc/__init__.py
Mobydoc/base.py
Mobydoc/utilities.py
Mobydoc/caracteristiques_physiques/caracteristiques_physiques.py
Mobydoc/caracteristiques_physiques/zone_generale.py
Mobydoc/classification/classification.py
Mobydoc/classification/zone_contexte.py
Mobydoc/classification/zone_identification.py
Mobydoc/classification/champs/auteur.py
Mobydoc/datation/datation.py
Mobydoc/datation/zone_generale.py
Mobydoc/datation_geologique/datation_geologique.py
Mobydoc/datation_geologique/zone_contexte.py
Mobydoc/datation_geologique/zone_generale.py
Mobydoc/localisation/localisation.py
Mobydoc/localisation/zone_contexte.py
Mobydoc/localisation/zone_generale.py
Mobydoc/localisation/zone_informations_systeme.py
Mobydoc/localisation/champ/zone_generale/multimedia.py
Mobydoc/moby/champ/date.py
Mobydoc/moby/tag/mobytag.py
Mobydoc/multimedia/multimedia.py
Mobydoc/multimedia/zone_generale.py
Mobydoc/notice_bibliographique/notice_bibliographique.py
Mobydoc/notice_bibliographique/zone_adresse_publication.py
Mobydoc/notice_bibliographique/zone_identification.py
Mobydoc/notice_bibliographique/zone_informations_systeme.py
Mobydoc/notice_bibliographique/zone_notes.py
Mobydoc/notice_bibliographique/zone_titre.py
Mobydoc/notice_bibliographique/champ/zone_titre/titre_propre.py
Mobydoc/personne/personne.py
Mobydoc/personne/zone_identification.py
Mobydoc/provenance/provenance.py
Mobydoc/provenance/zone_bibliographie.py
Mobydoc/provenance/zone_contexte.py
Mobydoc/provenance/zone_description.py
Mobydoc/provenance/zone_identification.py
Mobydoc/provenance/zone_informations_systeme.py
Mobydoc/provenance/champs/zone_identification/autres_coordonnees.py
Mobydoc/reference/autre_numero.py
Mobydoc/reference/conditions_pret.py
Mobydoc/reference/coordonnees.py
Mobydoc/reference/determination.py
Mobydoc/reference/discipline.py
Mobydoc/reference/etat.py
Mobydoc/reference/nature_specimen.py
Mobydoc/reference/qualificatif_date.py
Mobydoc/reference/qualificatif_lieu.py
Mobydoc/reference/rang_taxonomique.py
Mobydoc-0.0.28.dist-info/LICENSE.txt
Mobydoc-0.0.28.dist-info/METADATA
Mobydoc-0.0.28.dist-info/WHEEL
Mobydoc-0.0.28.dist-info/top_level.txt
Mobydoc-0.0.28.dist-info/RECORD
