Metadata-Version: 2.1
Name: Mobydoc
Version: 0.0.28
Summary: SqlAlchemy mapper to mobydoc database
Home-page: UNKNOWN
Author: Raphaël Jacquot
Author-email: raphael.jacquot@univ-grenoble-alpes.fr
License: UNKNOWN
Platform: UNKNOWN
Classifier: Development Status :: 3 - Alpha
Classifier: Intended Audience :: Developers
Classifier: License :: OSI Approved :: GNU General Public License v3 (GPLv3)
Classifier: Programming Language :: Python :: 3.7
Classifier: Programming Language :: Python :: 3.8
Requires-Python: >=3.7
License-File: LICENSE.txt
